apiverve_countryborders/__init__.py
apiverve_countryborders/apiClient.py
apiverve_countryborders/exceptions.py
apiverve_countryborders/setup.py
apiverve_countryborders/setup_dep.py
apiverve_countryborders/tests/__init__.py
apiverve_countryborders/tests/test_api.py
apiverve_countryborders-1.1.7.dist-info/LICENSE
apiverve_countryborders-1.1.7.dist-info/METADATA
apiverve_countryborders-1.1.7.dist-info/WHEEL
apiverve_countryborders-1.1.7.dist-info/top_level.txt
apiverve_countryborders-1.1.7.dist-info/RECORD
